render_engine_pg/__init__.py
render_engine_pg/__main__.py
render_engine_pg/connection.py
render_engine_pg/content_manager.py
render_engine_pg/page.py
render_engine_pg/parsers.py
render_engine_pg/py.typed
render_engine_pg/re_settings_parser.py
render_engine_pg/cli/__init__.py
render_engine_pg/cli/auto_classifier.py
render_engine_pg/cli/cli.py
render_engine_pg/cli/cli_common.py
render_engine_pg/cli/interactive_classifier.py
render_engine_pg/cli/populate_cli.py
render_engine_pg/cli/query_generator.py
render_engine_pg/cli/read_query_generator.py
render_engine_pg/cli/relationship_analyzer.py
render_engine_pg/cli/sql_cli.py
render_engine_pg/cli/sql_parser.py
render_engine_pg/cli/toml_generator.py
render_engine_pg/cli/types.py
render_engine_pg-2025.11.2.dist-info/licenses/LICENSE
render_engine_pg-2025.11.2.dist-info/METADATA
render_engine_pg-2025.11.2.dist-info/WHEEL
render_engine_pg-2025.11.2.dist-info/entry_points.txt
render_engine_pg-2025.11.2.dist-info/top_level.txt
render_engine_pg-2025.11.2.dist-info/RECORD
