Metadata-Version: 2.4
Name: render-engine-pg
Version: 2025.11.2
Summary: A PostgreSQL parser for the Render Engine
Requires-Python: >=3.11
License-File: LICENSE
Requires-Dist: psycopg[binary]>=3.0
Requires-Dist: render-engine>=2025.11.1a1
Requires-Dist: python-frontmatter>=1.0
Requires-Dist: render-engine-markdown>=2023.12.1
Requires-Dist: click>=8.3.0
Requires-Dist: tomli_w>=1.0.0
Provides-Extra: test
Requires-Dist: pytest>=7.0; extra == "test"
Requires-Dist: pytest-mock>=3.10; extra == "test"
Requires-Dist: mypy>=1.0; extra == "test"
Dynamic: license-file
